papermoon_mkdocs_plugins-0.1.0a1.dist-info/licenses/LICENSE
plugins/__init__.py
plugins/minify/__init__.py
plugins/minify/plugin.py
papermoon_mkdocs_plugins-0.1.0a1.dist-info/METADATA
papermoon_mkdocs_plugins-0.1.0a1.dist-info/WHEEL
papermoon_mkdocs_plugins-0.1.0a1.dist-info/entry_points.txt
papermoon_mkdocs_plugins-0.1.0a1.dist-info/top_level.txt
papermoon_mkdocs_plugins-0.1.0a1.dist-info/RECORD
