Metadata-Version: 2.4
Name: papermoon-mkdocs-plugins
Version: 0.1.0a1
Summary: A collection of mkdocs plugins
Author: Papermoon
License-Expression: BSD-2-Clause
Requires-Python: >=3.8
License-File: LICENSE
Requires-Dist: mkdocs>=1.6
Requires-Dist: mkdocs-material>=9.0
Requires-Dist: pymdown-extensions>=10.0
Requires-Dist: htmlmin>=0.1.12
Requires-Dist: jsmin>=3.0.1
Requires-Dist: csscompressor>=0.9.5
Dynamic: license-file
